{"data": [{"combustible_id": 2, "tipo_atencion": "Asistido", "zona_geografica_id": 1, "zonas_geografica_nombre": "Zona Norte", "region_id": "15", "region_nombre": "Arica y Parinacota", "estacion_direccion": "General Vel\u00e1squez 922", "comuna_id": "15101", "comuna_nombre": "Arica", "estacion_servicio_id": 20, "estacion_servicio_codigo": "pe1510103", "marca_nombre": "PETROBRAS", "combustible_precio": "1352.000", "en_mantencion": 0}, {"combustible_id": 2, "tipo_atencion": "Asistido", "zona_geografica_id": 1, "zonas_geografica_nombre": "Zona Norte", "region_id": "15", "region_nombre": "Arica y Parinacota", "estacion_direccion": "DIEGO PORTALES 1115", "comuna_id": "15101", "comuna_nombre": "Arica", "estacion_servicio_id": 7, "estacion_servicio_codigo": "co1510105", "marca_nombre": "COPEC", "combustible_precio": "1375.000", "en_mantencion": 0}, {"combustible_id": 2, "tipo_atencion": "Asistido", "zona_geografica_id": 1, "zonas_geografica_nombre": "Zona Norte", "region_id": "15", "region_nombre": "Arica y Parinacota", "estacion_direccion": " LUIS VALENTE ROSSI 1990", "comuna_id": "15101", "comuna_nombre": "Arica", "estacion_servicio_id": 5, "estacion_servicio_codigo": "co1510103", "marca_nombre": "COPEC", "combustible_precio": "1375.000", "en_mantencion": 0}, {"combustible_id": 10, "tipo_atencion": "Autoservicio", "zona_geografica_id": 1, "zonas_geografica_nombre": "Zona Norte", "region_id": "15", "region_nombre": "Arica y Parinacota", "estacion_direccion": "18 de Septiembre/Lastarria 1709", "comuna_id": "15101", "comuna_nombre": "Arica", "estacion_servicio_id": 18, "estacion_servicio_codigo": "pe1510101", "marca_nombre": "PETROBRAS", "combustible_precio": "1379.000", "en_mantencion": 0}, {"combustible_id": 2, "tipo_atencion": "Asistido", "zona_geografica_id": 1, "zonas_geografica_nombre": "Zona Norte", "region_id": "15", "region_nombre": "Arica y Parinacota", "estacion_direccion": "PANAMERICANA SUR 2824", "comuna_id": "15101", "comuna_nombre": "Arica", "estacion_servicio_id": 4, "estacion_servicio_codigo": "co1510102", "marca_nombre": "COPEC", "combustible_precio": "1381.000", "en_mantencion": 0}, {"combustible_id": 2, "tipo_atencion": "Asistido", "zona_geografica_id": 1, "zonas_geografica_nombre": "Zona Norte", "region_id": "15", "region_nombre": "Arica y Parinacota", "estacion_direccion": "Avda. Manuel Castillo Ibaceta 2920", "comuna_id": "15101", "comuna_nombre": "Arica", "estacion_servicio_id": 25, "estacion_servicio_codigo": "sh1510103", "marca_nombre": "SHELL", "combustible_precio": "1381.000", "en_mantencion": 0}, {"combustible_id": 2, "tipo_atencion": "Asistido", "zona_geografica_id": 1, "zonas_geografica_nombre": "Zona Norte", "region_id": "15", "region_nombre": "Arica y Parinacota", "estacion_direccion": "AV. DIEGO PORTALES 1072", "comuna_id": "15101", "comuna_nombre": "Arica", "estacion_servicio_id": 2, "estacion_servicio_codigo": "co1410106", "marca_nombre": "COPEC", "combustible_precio": "1381.000", "en_mantencion": 0}, {"combustible_id": 2, "tipo_atencion": "Asistido", "zona_geografica_id": 1, "zonas_geografica_nombre": "Zona Norte", "region_id": "15", "region_nombre": "Arica y Parinacota", "estacion_direccion": "Panamericana Norte 3545", "comuna_id": "15101", "comuna_nombre": "Arica", "estacion_servicio_id": 23, "estacion_servicio_codigo": "sh1510101", "marca_nombre": "SHELL", "combustible_precio": "1381.000", "en_mantencion": 0}, {"combustible_id": 2, "tipo_atencion": "Asistido", "zona_geografica_id": 1, "zonas_geografica_nombre": "Zona Norte", "region_id": "15", "region_nombre": "Arica y Parinacota", "estacion_direccion": "Av. Diego Portales 2462", "comuna_id": "15101", "comuna_nombre": "Arica", "estacion_servicio_id": 19, "estacion_servicio_codigo": "pe1510102", "marca_nombre": "PETROBRAS", "combustible_precio": "1381.000", "en_mantencion": 0}, {"combustible_id": 2, "tipo_atencion": "Asistido", "zona_geografica_id": 1, "zonas_geografica_nombre": "Zona Norte", "region_id": "15", "region_nombre": "Arica y Parinacota", "estacion_direccion": "18 DE SEPTIEMBRE 2401", "comuna_id": "15101", "comuna_nombre": "Arica", "estacion_servicio_id": 6, "estacion_servicio_codigo": "co1510104", "marca_nombre": "COPEC", "combustible_precio": "1381.000", "en_mantencion": 0}, {"combustible_id": 2, "tipo_atencion": "Asistido", "zona_geografica_id": 1, "zonas_geografica_nombre": "Zona Norte", "region_id": "15", "region_nombre": "Arica y Parinacota", "estacion_direccion": "SAN MART\u00cdN 699", "comuna_id": "15101", "comuna_nombre": "Arica", "estacion_servicio_id": 3, "estacion_servicio_codigo": "co1510101", "marca_nombre": "COPEC", "combustible_precio": "1381.000", "en_mantencion": 0}, {"combustible_id": 2, "tipo_atencion": "Asistido", "zona_geografica_id": 1, "zonas_geografica_nombre": "Zona Norte", "region_id": "15", "region_nombre": "Arica y Parinacota", "estacion_direccion": "Avda. Gonzalo Cerda 1330", "comuna_id": "15101", "comuna_nombre": "Arica", "estacion_servicio_id": 24, "estacion_servicio_codigo": "sh1510102", "marca_nombre": "SHELL", "combustible_precio": "1381.000", "en_mantencion": 0}, {"combustible_id": 2, "tipo_atencion": "Asistido", "zona_geografica_id": 1, "zonas_geografica_nombre": "Zona Norte", "region_id": "15", "region_nombre": "Arica y Parinacota", "estacion_direccion": "AVDA. CAPITAN AVALOS 2220", "comuna_id": "15101", "comuna_nombre": "Arica", "estacion_servicio_id": 21, "estacion_servicio_codigo": "pe1510104", "marca_nombre": "PETROBRAS", "combustible_precio": "1381.000", "en_mantencion": 0}, {"combustible_id": 2, "tipo_atencion": "Asistido", "zona_geografica_id": 1, "zonas_geografica_nombre": "Zona Norte", "region_id": "15", "region_nombre": "Arica y Parinacota", "estacion_direccion": "AV. SANTIAGO ARATA 3190", "comuna_id": "15101", "comuna_nombre": "Arica", "estacion_servicio_id": 8, "estacion_servicio_codigo": "co1510106", "marca_nombre": "COPEC", "combustible_precio": "1381.000", "en_mantencion": 0}]}